[
  {
    "ticker": "WING",
    "name": "WING",
    "market": "USA",
    "country": "--",
    "sector": "--",
    "price": 157.61,
    "currency": "USD",
    "high_52w": 388.14,
    "discount_52w": 59.4,
    "market_cap_mln": 4292.1,
    "volume_k": 1341.6,
    "smi": -54.95,
    "smi_ema": -61.29,
    "zone": "OVERSOLD",
    "signal": "Strong BUY",
    "eps_ttm": null,
    "sales_ttm_mln": 696.9,
    "quick_ratio": 3.26,
    "roic": 0.3291,
    "debt_equity": null,
    "gross_margin": 0.4868,
    "scanned_at": "2026-05-29T10:42:40.442777"
  },
  {
    "ticker": "RKT",
    "name": "RKT",
    "market": "USA",
    "country": "--",
    "sector": "--",
    "price": 14.4,
    "currency": "USD",
    "high_52w": 24.36,
    "discount_52w": 40.9,
    "market_cap_mln": 40743.8,
    "volume_k": 25444.4,
    "smi": -39.91,
    "smi_ema": -42.48,
    "zone": "Bearish",
    "signal": "Strong BUY",
    "eps_ttm": null,
    "sales_ttm_mln": 6257.0,
    "quick_ratio": null,
    "roic": null,
    "debt_equity": 0.68,
    "gross_margin": null,
    "scanned_at": "2026-05-29T10:42:44.898558"
  },
  {
    "ticker": "BRR",
    "name": "BRR",
    "market": "USA",
    "country": "--",
    "sector": "--",
    "price": 2.28,
    "currency": "USD",
    "high_52w": 16.25,
    "discount_52w": 86.0,
    "market_cap_mln": 206.5,
    "volume_k": 1145.5,
    "smi": -50.66,
    "smi_ema": -60.16,
    "zone": "OVERSOLD",
    "signal": "Strong BUY",
    "eps_ttm": null,
    "sales_ttm_mln": null,
    "quick_ratio": 87.21,
    "roic": null,
    "debt_equity": 0.515,
    "gross_margin": null,
    "scanned_at": "2026-05-29T10:42:44.913180"
  },
  {
    "ticker": "KROS",
    "name": "KROS",
    "market": "USA",
    "country": "--",
    "sector": "--",
    "price": 11.39,
    "currency": "USD",
    "high_52w": 22.55,
    "discount_52w": 49.5,
    "market_cap_mln": 225.4,
    "volume_k": 428.4,
    "smi": -33.83,
    "smi_ema": -45.26,
    "zone": "Bearish",
    "signal": "Strong BUY",
    "eps_ttm": null,
    "sales_ttm_mln": 244.1,
    "quick_ratio": 15.45,
    "roic": 2.1191,
    "debt_equity": 0.056,
    "gross_margin": null,
    "scanned_at": "2026-05-29T10:42:48.696099"
  },
  {
    "ticker": "CATX",
    "name": "CATX",
    "market": "USA",
    "country": "--",
    "sector": "--",
    "price": 4.05,
    "currency": "USD",
    "high_52w": 6.16,
    "discount_52w": 34.3,
    "market_cap_mln": 461.9,
    "volume_k": 1411.2,
    "smi": -54.89,
    "smi_ema": -55.59,
    "zone": "OVERSOLD",
    "signal": "Strong BUY",
    "eps_ttm": null,
    "sales_ttm_mln": 0.0,
    "quick_ratio": null,
    "roic": null,
    "debt_equity": null,
    "gross_margin": null,
    "scanned_at": "2026-05-29T10:42:54.463864"
  },
  {
    "ticker": "AJG",
    "name": "AJG",
    "market": "USA",
    "country": "--",
    "sector": "--",
    "price": 202.65,
    "currency": "USD",
    "high_52w": 351.23,
    "discount_52w": 42.3,
    "market_cap_mln": 52069.3,
    "volume_k": 1991.8,
    "smi": -37.29,
    "smi_ema": -38.29,
    "zone": "Bearish",
    "signal": "Strong BUY",
    "eps_ttm": null,
    "sales_ttm_mln": null,
    "quick_ratio": null,
    "roic": null,
    "debt_equity": null,
    "gross_margin": null,
    "scanned_at": "2026-05-29T10:42:54.522499"
  },
  {
    "ticker": "NBP",
    "name": "NBP",
    "market": "USA",
    "country": "--",
    "sector": "--",
    "price": 1.87,
    "currency": "USD",
    "high_52w": 6.79,
    "discount_52w": 72.5,
    "market_cap_mln": 216.3,
    "volume_k": 1004.4,
    "smi": -79.91,
    "smi_ema": -78.44,
    "zone": "OVERSOLD",
    "signal": "Turning Up",
    "eps_ttm": null,
    "sales_ttm_mln": null,
    "quick_ratio": null,
    "roic": null,
    "debt_equity": null,
    "gross_margin": null,
    "scanned_at": "2026-05-29T10:42:55.849474"
  },
  {
    "ticker": "DG",
    "name": "DG",
    "market": "USA",
    "country": "--",
    "sector": "--",
    "price": 109.9,
    "currency": "USD",
    "high_52w": 158.23,
    "discount_52w": 30.5,
    "market_cap_mln": 24202.9,
    "volume_k": 3480.4,
    "smi": -72.14,
    "smi_ema": -77.43,
    "zone": "OVERSOLD",
    "signal": "Strong BUY",
    "eps_ttm": null,
    "sales_ttm_mln": null,
    "quick_ratio": null,
    "roic": null,
    "debt_equity": null,
    "gross_margin": null,
    "scanned_at": "2026-05-29T10:42:55.853657"
  },
  {
    "ticker": "MBC",
    "name": "MBC",
    "market": "USA",
    "country": "--",
    "sector": "--",
    "price": 9.08,
    "currency": "USD",
    "high_52w": 14.22,
    "discount_52w": 36.1,
    "market_cap_mln": 1162.1,
    "volume_k": 2822.2,
    "smi": -24.85,
    "smi_ema": -38.67,
    "zone": "Bearish",
    "signal": "Strong BUY",
    "eps_ttm": null,
    "sales_ttm_mln": null,
    "quick_ratio": null,
    "roic": null,
    "debt_equity": null,
    "gross_margin": null,
    "scanned_at": "2026-05-29T10:42:55.854657"
  },
  {
    "ticker": "IAG",
    "name": "IAG",
    "market": "USA",
    "country": "--",
    "sector": "--",
    "price": 17.36,
    "currency": "USD",
    "high_52w": 24.87,
    "discount_52w": 30.2,
    "market_cap_mln": 10034.1,
    "volume_k": 7073.9,
    "smi": -55.85,
    "smi_ema": -54.26,
    "zone": "OVERSOLD",
    "signal": "Turning Up",
    "eps_ttm": null,
    "sales_ttm_mln": 2852.8,
    "quick_ratio": null,
    "roic": null,
    "debt_equity": null,
    "gross_margin": 0.4228,
    "scanned_at": "2026-05-29T10:42:56.048292"
  }
]