[
  {
    "ticker": "MNSO",
    "name": "MINISO Group Holding Limited",
    "market": "USA",
    "country": "China",
    "sector": "Consumer Cyclical",
    "price": 13.41,
    "currency": "USD",
    "high_52w": 26.74,
    "discount_52w": 49.8,
    "market_cap_mln": 4178.2,
    "volume_k": 485.3,
    "smi": -71.38,
    "smi_ema": -75.11,
    "zone": "OVERSOLD",
    "signal": "Strong BUY",
    "divergence_bull": false,
    "divergence_desc": "",
    "eps_ttm": 1.03,
    "sales_ttm_mln": 16994.0,
    "quick_ratio": 1.55,
    "roic": 0.4181,
    "debt_equity": 0.301,
    "gross_margin": 0.4494,
    "scanned_at": "2026-06-04T14:20:06.253656",
    "tech_score": 8
  },
  {
    "ticker": "DPZ",
    "name": "DPZ",
    "market": "USA",
    "country": "--",
    "sector": "--",
    "price": 310.8,
    "currency": "USD",
    "high_52w": 496.0,
    "discount_52w": 37.3,
    "market_cap_mln": 10337.8,
    "volume_k": 957.2,
    "smi": -72.71,
    "smi_ema": -73.3,
    "zone": "OVERSOLD",
    "signal": "Strong BUY",
    "divergence_bull": false,
    "divergence_desc": "",
    "eps_ttm": null,
    "sales_ttm_mln": 4940.0,
    "quick_ratio": 1.5,
    "roic": 0.7072,
    "debt_equity": null,
    "gross_margin": 0.3995,
    "scanned_at": "2026-06-04T14:19:49.984402",
    "tech_score": 7
  },
  {
    "ticker": "PODD",
    "name": "PODD",
    "market": "USA",
    "country": "--",
    "sector": "--",
    "price": 149.79,
    "currency": "USD",
    "high_52w": 354.88,
    "discount_52w": 57.8,
    "market_cap_mln": 10375.2,
    "volume_k": 1270.4,
    "smi": -83.89,
    "smi_ema": -84.82,
    "zone": "OVERSOLD",
    "signal": "Strong BUY",
    "divergence_bull": false,
    "divergence_desc": "",
    "eps_ttm": null,
    "sales_ttm_mln": 2708.1,
    "quick_ratio": 2.15,
    "roic": 0.1922,
    "debt_equity": 0.626,
    "gross_margin": 0.7163,
    "scanned_at": "2026-06-04T14:19:52.680274",
    "tech_score": 7
  },
  {
    "ticker": "RMD",
    "name": "RMD",
    "market": "USA",
    "country": "--",
    "sector": "--",
    "price": 193.49,
    "currency": "USD",
    "high_52w": 293.81,
    "discount_52w": 34.1,
    "market_cap_mln": 28067.0,
    "volume_k": 1273.5,
    "smi": -71.45,
    "smi_ema": -74.17,
    "zone": "OVERSOLD",
    "signal": "Strong BUY",
    "divergence_bull": false,
    "divergence_desc": "",
    "eps_ttm": null,
    "sales_ttm_mln": 5146.3,
    "quick_ratio": 2.53,
    "roic": 0.237,
    "debt_equity": 0.143,
    "gross_margin": 0.5936,
    "scanned_at": "2026-06-04T14:19:53.565635",
    "tech_score": 7
  },
  {
    "ticker": "THO",
    "name": "THO",
    "market": "USA",
    "country": "--",
    "sector": "--",
    "price": 76.3,
    "currency": "USD",
    "high_52w": 122.83,
    "discount_52w": 37.9,
    "market_cap_mln": 3971.9,
    "volume_k": 760.1,
    "smi": -33.97,
    "smi_ema": -47.29,
    "zone": "Bearish",
    "signal": "Strong BUY",
    "divergence_bull": true,
    "divergence_desc": "div_bull (cena -0.8%, SMI +2.0)",
    "eps_ttm": null,
    "sales_ttm_mln": null,
    "quick_ratio": null,
    "roic": null,
    "debt_equity": null,
    "gross_margin": null,
    "scanned_at": "2026-06-04T14:20:09.930427",
    "tech_score": 6
  },
  {
    "ticker": "ISSC",
    "name": "Innovative Solutions and Suppor",
    "market": "USA",
    "country": "United States",
    "sector": "Industrials",
    "price": 17.32,
    "currency": "USD",
    "high_52w": 30.94,
    "discount_52w": 44.0,
    "market_cap_mln": 309.9,
    "volume_k": 621.7,
    "smi": -73.25,
    "smi_ema": -71.43,
    "zone": "OVERSOLD",
    "signal": "Turning Up",
    "divergence_bull": false,
    "divergence_desc": "",
    "eps_ttm": 0.95,
    "sales_ttm_mln": 84.3,
    "quick_ratio": 1.5,
    "roic": 0.1872,
    "debt_equity": 0.374,
    "gross_margin": 0.4806,
    "scanned_at": "2026-06-04T14:19:59.865575",
    "tech_score": 5
  },
  {
    "ticker": "CIGI",
    "name": "Colliers International Group In",
    "market": "USA",
    "country": "Canada",
    "sector": "Real Estate",
    "price": 97.58,
    "currency": "USD",
    "high_52w": 171.51,
    "discount_52w": 43.1,
    "market_cap_mln": 4986.7,
    "volume_k": 307.1,
    "smi": -69.29,
    "smi_ema": -66.38,
    "zone": "OVERSOLD",
    "signal": "Turning Up",
    "divergence_bull": true,
    "divergence_desc": "div_bull (cena -7.9%, SMI +10.1)",
    "eps_ttm": 1.63,
    "sales_ttm_mln": 5558.5,
    "quick_ratio": null,
    "roic": null,
    "debt_equity": null,
    "gross_margin": 0.4005,
    "scanned_at": "2026-06-04T14:20:09.664898",
    "tech_score": 5
  },
  {
    "ticker": "HDB",
    "name": "HDB",
    "market": "USA",
    "country": "--",
    "sector": "--",
    "price": 24.16,
    "currency": "USD",
    "high_52w": 39.81,
    "discount_52w": 39.3,
    "market_cap_mln": 124001.5,
    "volume_k": 9843.7,
    "smi": -69.37,
    "smi_ema": -69.04,
    "zone": "OVERSOLD",
    "signal": "Turning Up",
    "divergence_bull": false,
    "divergence_desc": "",
    "eps_ttm": null,
    "sales_ttm_mln": 2371508.2,
    "quick_ratio": null,
    "roic": null,
    "debt_equity": 0.954,
    "gross_margin": null,
    "scanned_at": "2026-06-04T14:19:49.461360",
    "tech_score": 2
  }
]